setup.py
distributions_iyobosa/Binomialdistribution.py
distributions_iyobosa/Generaldistribution.py
distributions_iyobosa/Guassiandistribution.py
distributions_iyobosa/__init__.py
distributions_iyobosa.egg-info/PKG-INFO
distributions_iyobosa.egg-info/SOURCES.txt
distributions_iyobosa.egg-info/dependency_links.txt
distributions_iyobosa.egg-info/not-zip-safe
distributions_iyobosa.egg-info/top_level.txt