Metadata-Version: 1.0
Name: distributions-iyobosa
Version: 0.1
Summary: Gaussian and Binomial distributions
Home-page: UNKNOWN
Author: Iyobosa Evbayowieru
Author-email: iyobo247@gmail.com
License: UNKNOWN
Platform: UNKNOWN
